MANIFEST.in
README.txt
setup.py
docs/CONTRIBUTORS.txt
docs/HISTORY.txt
docs/LICENSE.ZPL
docs/LICENSE.txt
docs/README.txt
src/ztfy/__init__.py
src/ztfy.bootstrap.egg-info/PKG-INFO
src/ztfy.bootstrap.egg-info/SOURCES.txt
src/ztfy.bootstrap.egg-info/dependency_links.txt
src/ztfy.bootstrap.egg-info/entry_points.txt
src/ztfy.bootstrap.egg-info/namespace_packages.txt
src/ztfy.bootstrap.egg-info/not-zip-safe
src/ztfy.bootstrap.egg-info/requires.txt
src/ztfy.bootstrap.egg-info/top_level.txt
src/ztfy/bootstrap/__init__.py
src/ztfy/bootstrap/configure.zcml
src/ztfy/bootstrap/layer.py
src/ztfy/bootstrap/blog/__init__.py
src/ztfy/bootstrap/blog/configure.zcml
src/ztfy/bootstrap/blog/layer.py
src/ztfy/bootstrap/blog/skin/__init__.py
src/ztfy/bootstrap/blog/skin/configure.zcml
src/ztfy/bootstrap/blog/skin/resources/css/ztfy.bootstrap.blog.css
src/ztfy/bootstrap/blog/skin/resources/css/ztfy.bootstrap.blog.min.css
src/ztfy/bootstrap/blog/skin/templates/layout.pt
src/ztfy/bootstrap/blog/skin/templates/section_index.pt
src/ztfy/bootstrap/blog/skin/templates/section_sections.pt
src/ztfy/bootstrap/blog/skin/templates/site_index.pt
src/ztfy/bootstrap/blog/skin/templates/site_layout.pt
src/ztfy/bootstrap/blog/skin/templates/topic_index.pt
src/ztfy/bootstrap/blog/skin/templates/topic_preview.pt
src/ztfy/bootstrap/blog/skin/templates/topic_tags.pt
src/ztfy/bootstrap/blog/skin/viewlets/__init__.py
src/ztfy/bootstrap/blog/skin/viewlets/configure.zcml
src/ztfy/bootstrap/blog/skin/viewlets/footer/__init__.py
src/ztfy/bootstrap/blog/skin/viewlets/footer/configure.zcml
src/ztfy/bootstrap/blog/skin/viewlets/footer/interfaces.py
src/ztfy/bootstrap/blog/skin/viewlets/footer/templates/signature.pt
src/ztfy/bootstrap/blog/skin/viewlets/header/__init__.py
src/ztfy/bootstrap/blog/skin/viewlets/header/configure.zcml
src/ztfy/bootstrap/blog/skin/viewlets/header/interfaces.py
src/ztfy/bootstrap/blog/skin/viewlets/header/login.py
src/ztfy/bootstrap/blog/skin/viewlets/header/sections.py
src/ztfy/bootstrap/blog/skin/viewlets/header/templates/brand.pt
src/ztfy/bootstrap/blog/skin/viewlets/header/templates/login.pt
src/ztfy/bootstrap/blog/skin/viewlets/header/templates/navbar.pt
src/ztfy/bootstrap/blog/skin/viewlets/header/templates/sections.pt
src/ztfy/bootstrap/doctests/README.txt
src/ztfy/bootstrap/locales/ztfy.bootstrap.pot
