Metadata-Version: 1.1
Name: ztfy.bootstrap
Version: 0.1.5
Summary: Bootstrap based ZTFY skin
Home-page: http://hg.ztfy.org/ztfy.bootstrap
Author: Thierry Florac
Author-email: tflorac@ulthar.net
License: zpl
Keywords: ZTFY bootstrap skin glyphicons
Platform: UNKNOWN
Classifier: Development Status :: 4 - Beta
Classifier: Framework :: Zope3
Classifier: Intended Audience :: Developers
Classifier: License :: OSI Approved :: Zope Public License
Classifier: Programming Language :: Python
Classifier: Topic :: Software Development :: User Interfaces
